{
  "codeLens.enable": true,
  "languageserver": {
    "clangd": {
      "command": "clangd",
      "rootPatterns": [
        "compile_flags.txt",
        "compile_commands.json"
      ],
      "filetypes": [
        "c",
        "cc",
        "cpp",
        "c++",
        "objc",
        "objcpp"
      ]
    }
  },
  "coc.preferences.formatOnSaveFiletypes": [
    "python",
    "javascript",
    "javascriptreact",
    "typescriptreact",
    "css",
    "cpp",
    "c"
  ],
  "explorer.keyMappings.global": {
    "u": "gotoParent"
  },
  "post.root": "~/work/posts",
  "python.formatting.provider": "black",
  "git.enableGutters": false,
  "snippets.userSnippetsDirectory": "~/.config/nvim/snippets/",
  "coc.preferences.formatOnType": true,
  "explorer.icon.enableNerdfont": true,
  "explorer.filename.colored.enable": false
}
